przelewy24/__init__.py
przelewy24/client.py
przelewy24/exceptions.py
przelewy24/models.py
przelewy24_python-1.0.0.dist-info/licenses/LICENSE
przelewy24_python-1.0.0.dist-info/METADATA
przelewy24_python-1.0.0.dist-info/WHEEL
przelewy24_python-1.0.0.dist-info/top_level.txt
przelewy24_python-1.0.0.dist-info/RECORD
