Metadata-Version: 2.4
Name: przelewy24-python
Version: 1.0.0
Summary: Python SDK for Przelewy24 payment gateway
Home-page: https://github.com/ItsRaelx/PythonPrzelewy24
Author: Dawid Iwański
Author-email: d.iwanski@secc.me
Project-URL: Bug Reports, https://github.com/ItsRaelx/PythonPrzelewy24/issues
Project-URL: Source, https://github.com/ItsRaelx/PythonPrzelewy24
Project-URL: Documentation, https://github.com/ItsRaelx/PythonPrzelewy24
Keywords: przelewy24 payment gateway api sdk
Classifier: Development Status :: 4 - Beta
Classifier: Intended Audience :: Developers
Classifier: License :: OSI Approved :: MIT License
Classifier: Operating System :: OS Independent
Classifier: Programming Language :: Python :: 3
Classifier: Programming Language :: Python :: 3.7
Classifier: Programming Language :: Python :: 3.8
Classifier: Programming Language :: Python :: 3.9
Classifier: Programming Language :: Python :: 3.10
Classifier: Programming Language :: Python :: 3.11
Classifier: Topic :: Software Development :: Libraries :: Python Modules
Classifier: Topic :: Office/Business :: Financial :: Point-Of-Sale
Requires-Python: >=3.7
License-File: LICENSE
Requires-Dist: requests>=2.25.0
Requires-Dist: dataclasses>=0.6; python_version < "3.7"
Dynamic: author
Dynamic: author-email
Dynamic: classifier
Dynamic: description
Dynamic: description-content-type
Dynamic: home-page
Dynamic: keywords
Dynamic: license-file
Dynamic: project-url
Dynamic: requires-dist
Dynamic: requires-python
Dynamic: summary
